espeak_phonemizer/__init__.py
espeak_phonemizer/__main__.py
espeak_phonemizer/espeak-ng/espeak-ng-data/af_dict
espeak_phonemizer/espeak-ng/espeak-ng-data/am_dict
espeak_phonemizer/espeak-ng/espeak-ng-data/an_dict
espeak_phonemizer/espeak-ng/espeak-ng-data/ar_dict
espeak_phonemizer/espeak-ng/espeak-ng-data/as_dict
espeak_phonemizer/espeak-ng/espeak-ng-data/az_dict
espeak_phonemizer/espeak-ng/espeak-ng-data/ba_dict
espeak_phonemizer/espeak-ng/espeak-ng-data/be_dict
espeak_phonemizer/espeak-ng/espeak-ng-data/bg_dict
espeak_phonemizer/espeak-ng/espeak-ng-data/bn_dict
espeak_phonemizer/espeak-ng/espeak-ng-data/bpy_dict
espeak_phonemizer/espeak-ng/espeak-ng-data/bs_dict
espeak_phonemizer/espeak-ng/espeak-ng-data/ca_dict
espeak_phonemizer/espeak-ng/espeak-ng-data/chr_dict
espeak_phonemizer/espeak-ng/espeak-ng-data/cmn_dict
espeak_phonemizer/espeak-ng/espeak-ng-data/cs_dict
espeak_phonemizer/espeak-ng/espeak-ng-data/cv_dict
espeak_phonemizer/espeak-ng/espeak-ng-data/cy_dict
espeak_phonemizer/espeak-ng/espeak-ng-data/da_dict
espeak_phonemizer/espeak-ng/espeak-ng-data/de_dict
espeak_phonemizer/espeak-ng/espeak-ng-data/el_dict
espeak_phonemizer/espeak-ng/espeak-ng-data/en_dict
espeak_phonemizer/espeak-ng/espeak-ng-data/eo_dict
espeak_phonemizer/espeak-ng/espeak-ng-data/es_dict
espeak_phonemizer/espeak-ng/espeak-ng-data/et_dict
espeak_phonemizer/espeak-ng/espeak-ng-data/eu_dict
espeak_phonemizer/espeak-ng/espeak-ng-data/fa_dict
espeak_phonemizer/espeak-ng/espeak-ng-data/fi_dict
espeak_phonemizer/espeak-ng/espeak-ng-data/fr_dict
espeak_phonemizer/espeak-ng/espeak-ng-data/ga_dict
espeak_phonemizer/espeak-ng/espeak-ng-data/gd_dict
espeak_phonemizer/espeak-ng/espeak-ng-data/gn_dict
espeak_phonemizer/espeak-ng/espeak-ng-data/grc_dict
espeak_phonemizer/espeak-ng/espeak-ng-data/gu_dict
espeak_phonemizer/espeak-ng/espeak-ng-data/hak_dict
espeak_phonemizer/espeak-ng/espeak-ng-data/haw_dict
espeak_phonemizer/espeak-ng/espeak-ng-data/he_dict
espeak_phonemizer_windows-1.0.4.dist-info/LICENSE
espeak_phonemizer_windows-1.0.4.dist-info/METADATA
espeak_phonemizer_windows-1.0.4.dist-info/WHEEL
espeak_phonemizer_windows-1.0.4.dist-info/RECORD
