Metadata-Version: 2.1
Name: espeak-phonemizer-windows
Version: 1.0.4
Summary: Uses espeak-ng to transform text into IPA phonemes.
Home-page: https://github.com/mush42/espeak-phonemizer-windows
License: GNU GENERAL PUBLIC LICENSE
Keywords: espeak,phonemes,ipa,nlp
Author: mush42
Author-email: ibnomer2011@hotmail.com
Requires-Python: >=3.8,<4.0
Classifier: Development Status :: 5 - Production/Stable
Classifier: License :: Other/Proprietary License
Classifier: Operating System :: Microsoft :: Windows
Classifier: Programming Language :: Python :: 3
Classifier: Programming Language :: Python :: 3.8
Classifier: Programming Language :: Python :: 3.9
Classifier: Programming Language :: Python :: 3.10
Classifier: Programming Language :: Python :: 3.11
Classifier: Topic :: Software Development :: Libraries :: Python Modules
Classifier: Topic :: Text Processing :: Linguistic
Project-URL: Repository, https://github.com/mush42/espeak-phonemizer-windows
